{"dbId":"204998","name":"Cell death signalling via NRAGE NRIF and NADE","children":[{"dbId":"193648","name":"NRAGE signals death through JNK","children":[],"size":1,"symbols":["NGF","ARHGEF17","FGD1","VAV1","VAV2","VAV3","ARHGEF6","PLEKHG2","ARHGEF9","TIAM2","TIAM1","NGFR","TRIO","MCF2L","ECT2","PLEKHG5","ARHGAP4","ARHGEF2","ARHGEF11","SOS1","SOS2","ARHGEF18","MAGED1","ABR","AKAP13","ARHGEF3","ARHGEF4","ARHGEF7","ARHGEF12","ARHGEF16","FGD2","FGD3","FGD4","AATF","ITSN1","KALRN","MCF2","NET1","NGEF","OBSCN","BCL2L11","BAD","BAD","BCL2L11","MAPK8","MAPK8","MAPK8","RAC1","RASGRF2"],"gallusOrth":{"sharedSymbols":["NGF","ARHGEF17","VAV1","VAV2","VAV3","ARHGEF6","ARHGEF9","TIAM2","TIAM1","NGFR","TRIO","MCF2L","ECT2","PLEKHG5","ARHGEF2","ARHGEF11","SOS1","SOS2","ARHGEF18","ABR","AKAP13","ARHGEF3","ARHGEF4","ARHGEF7","ARHGEF12","ARHGEF16","FGD2","FGD3","FGD4","AATF","ITSN1","KALRN","MCF2","NET1","NGEF","OBSCN","BCL2L11","BAD","BAD","BCL2L11","MAPK8","MAPK8","MAPK8","RAC1","RASGRF2"],"count":45,"type":"Part"}},{"dbId":"205043","name":"NRIF signals cell death from the nucleus","children":[],"size":1,"symbols":["NGF","PSENEN","PSEN2","NCSTN","RPS27A","UBA52","UBB","UBB","UBB","UBC","NGFR","UBC","UBC","UBC","UBC","UBC","UBC","UBC","UBC","SQSTM1","ITGB3BP","ITGB3BP","RPS27A","UBA52","UBB","UBB","UBB","UBC","UBC","UBC","UBC","TRAF6","UBC","UBC","UBC","UBC","UBC","SQSTM1","MAPK8","MAPK8","APH1B","APH1A"],"gallusOrth":{"sharedSymbols":["NGF","PSENEN","PSEN2","NCSTN","RPS27A","UBA52","UBB","UBB","UBB","NGFR","SQSTM1","ITGB3BP","ITGB3BP","RPS27A","UBA52","UBB","UBB","UBB","TRAF6","SQSTM1","MAPK8","MAPK8","APH1A"],"count":23,"type":"Part"}},{"dbId":"205025","name":"NADE modulates death signalling","children":[],"size":1,"symbols":["NGF","CASP3","YWHAE","NGFR","NGFRAP1","CASP3","CASP2","CASP2","CASP2","CASP3"],"gallusOrth":{"sharedSymbols":["NGF","CASP3","YWHAE","NGFR","CASP3","CASP2","CASP2","CASP2","CASP3"],"count":9,"type":"Part"}}],"symbols":["NGF","ARHGEF17","YWHAE","FGD1","VAV1","VAV2","VAV3","ARHGEF6","PLEKHG2","ARHGEF9","TIAM2","TIAM1","NGFR","TRIO","MCF2L","ECT2","PLEKHG5","ARHGAP4","ARHGEF2","ARHGEF11","SOS1","SOS2","ARHGEF18","MAGED1","ABR","AKAP13","ARHGEF3","ARHGEF4","ARHGEF7","ARHGEF12","ARHGEF16","FGD2","FGD3","FGD4","AATF","ITSN1","KALRN","MCF2","NET1","NGEF","OBSCN","BCL2L11","BAD","BAD","BCL2L11","MAPK8","MAPK8","ITGB3BP","TRAF6","APH1B","APH1A","PSENEN","PSEN2","NCSTN","MAPK8","RPS27A","UBA52","UBB","UBB","UBB","UBC","UBC","UBC","UBC","UBC","RAC1","UBC","UBC","UBC","UBC","SQSTM1","ITGB3BP","RPS27A","UBA52","UBB","UBB","UBB","UBC","UBC","UBC","UBC","UBC","UBC","UBC","UBC","RASGRF2","UBC","SQSTM1","NGFRAP1","CASP3","CASP2","CASP2","CASP2","CASP3","CASP3"],"gallusOrth":{"sharedSymbols":["NGF","ARHGEF17","YWHAE","VAV1","VAV2","VAV3","ARHGEF6","ARHGEF9","TIAM2","TIAM1","NGFR","TRIO","MCF2L","ECT2","PLEKHG5","ARHGEF2","ARHGEF11","SOS1","SOS2","ARHGEF18","ABR","AKAP13","ARHGEF3","ARHGEF4","ARHGEF7","ARHGEF12","ARHGEF16","FGD2","FGD3","FGD4","AATF","ITSN1","KALRN","MCF2","NET1","NGEF","OBSCN","BCL2L11","BAD","BAD","BCL2L11","MAPK8","MAPK8","ITGB3BP","TRAF6","APH1A","PSENEN","PSEN2","NCSTN","MAPK8","RPS27A","UBA52","UBB","UBB","UBB","RAC1","SQSTM1","ITGB3BP","RPS27A","UBA52","UBB","UBB","UBB","RASGRF2","SQSTM1","CASP3","CASP2","CASP2","CASP2","CASP3","CASP3"],"count":71,"type":"Part"}}