{"dbId":"2559582","name":"Senescence-Associated Secretory Phenotype (SASP)","children":[],"size":1,"symbols":["CDC27","CDK4","CDK6","JUN","FOS","IGFBP7","ANAPC1","ANAPC11","UBE2E1","UBE2C","CDC23","ANAPC4","CDC26","CDC16","ANAPC2","CCNA1","CDK2","CDKN1A","CDKN1B","FZR1","EHMT1","EHMT2","RPS27A","UBA52","CCNA2","UBB","UBB","UBB","UBC","UBC","UBC","UBC","UBC","UBC","UBC","CDK2","UBC","UBC","HIST1H3A","HIST2H3A","H3F3A","HIST1H2BK","HIST3H2BB","HIST1H2BA","FZR1","HIST1H2BC","HIST1H2BD","HIST1H2BL","HIST1H2BN","HIST1H2BM","HIST1H2BB","HIST1H2BH","HIST1H2BO","HIST2H2BE","HIST1H2BJ","ANAPC5","H2BFS","H2AFB1","HIST1H2AB","HIST1H2AJ","HIST1H2AD","HIST1H2AC","HIST2H2AA3","HIST2H2AC","H2AFX","UBE2D1","H2AFZ","HIST1H4A","HIST1H3A","HIST2H3A","H3F3A","RPS6KA1","RPS6KA2","RPS6KA3","ANAPC10","RPS6KA1","RPS6KA2","RPS6KA3","MAPK7","MAPK3","MAPK1","CEBPB","CEBPB","ANAPC7","CEBPB","IL6","STAT3","IL8","CDKN2B","CDKN2A","CDKN2C","CDKN2D"],"gallusOrth":{"sharedSymbols":["CDC27","CDK4","CDK6","JUN","FOS","IGFBP7","ANAPC1","ANAPC11","UBE2E1","UBE2C","CDC23","ANAPC4","CDC26","CDC16","ANAPC2","CCNA1","CDK2","CDKN1A","CDKN1B","FZR1","EHMT1","EHMT2","RPS27A","UBA52","CCNA2","UBB","UBB","UBB","UBC","UBC","UBC","UBC","UBC","UBC","UBC","CDK2","UBC","UBC","HIST1H3A","HIST2H3A","H3F3A","HIST1H2BK","HIST3H2BB","HIST1H2BA","FZR1","HIST1H2BC","HIST1H2BD","HIST1H2BL","HIST1H2BN","HIST1H2BM","HIST1H2BB","HIST1H2BH","HIST1H2BO","HIST2H2BE","HIST1H2BJ","ANAPC5","H2BFS","H2AFB1","HIST1H2AB","HIST1H2AJ","HIST1H2AD","HIST1H2AC","HIST2H2AA3","HIST2H2AC","H2AFX","UBE2D1","H2AFZ","HIST1H4A","HIST1H3A","HIST2H3A","H3F3A","RPS6KA1","RPS6KA2","RPS6KA3","ANAPC10","RPS6KA1","RPS6KA2","RPS6KA3","MAPK7","MAPK3","MAPK1","CEBPB","CEBPB","ANAPC7","CEBPB","IL6","STAT3","IL8","CDKN2B","CDKN2A","CDKN2C","CDKN2D"],"count":92,"type":"Complete"}}