{"dbId":"964739","name":"N-glycan trimming and elongation in the cis-Golgi","children":[{"dbId":"964827","name":"Progressive trimming of alpha-12-linked mannose residues from Man987GlcNAc2 to produce Man5GlcNAc2","children":[],"size":1,"symbols":["MAN1A1","MAN1A2","MAN1C1"],"gallusOrth":{"sharedSymbols":["MAN1A1","MAN1A2","MAN1C1"],"count":3,"type":"Complete"}}],"symbols":["MANEA","MAN1A1","MAN1A2","MAN1C1","MGAT1"],"gallusOrth":{"sharedSymbols":["MANEA","MAN1A1","MAN1A2","MAN1C1","MGAT1"],"count":5,"type":"Complete"}}